[
  {
    "sender": "Bushra Khan",
    "text": "So wanted to go",
    "time": "Nov 16, 2024 12:51 am",
    "reactions": [],
    "kind": "msg"
  },
  {
    "sender": "Aamir | عامر",
    "text": "Understood ma’amYou can tell you sister like she can come with you as wellIt’s just for some time if they not letting you go on your own",
    "time": "Nov 16, 2024 12:52 am",
    "reactions": [],
    "kind": "msg"
  },
  {
    "sender": "Bushra Khan",
    "text": "😔 she has work so won’t come",
    "time": "Nov 16, 2024 12:52 am",
    "reactions": [],
    "kind": "msg"
  },
  {
    "sender": "Bushra Khan",
    "text": "It’s okay",
    "time": "Nov 16, 2024 12:53 am",
    "reactions": [],
    "kind": "msg"
  },
  {
    "sender": "Aamir | عامر",
    "text": "Don’t like this",
    "time": "Nov 16, 2024 12:53 am",
    "reactions": [
      {
        "reactor": "Bushra Khan",
        "emoji": "😢"
      }
    ],
    "kind": "msg"
  },
  {
    "sender": "Aamir | عامر",
    "text": "If I said yes then what you gonna do ma’am",
    "time": "Nov 16, 2024 12:54 am",
    "reactions": [],
    "kind": "msg"
  },
  {
    "sender": "Bushra Khan",
    "text": "I was gonna say I went Arisha",
    "time": "Nov 16, 2024 12:54 am",
    "reactions": [],
    "kind": "msg"
  },
  {
    "sender": "Aamir | عامر",
    "text": "Okkay",
    "time": "Nov 16, 2024 12:54 am",
    "reactions": [],
    "kind": "msg"
  },
  {
    "sender": "Bushra Khan",
    "text": "But I won’t",
    "time": "Nov 16, 2024 12:55 am",
    "reactions": [],
    "kind": "msg"
  },
  {
    "sender": "Aamir | عامر",
    "text": "I know",
    "time": "Nov 16, 2024 12:55 am",
    "reactions": [],
    "kind": "msg"
  },
  {
    "sender": "Aamir | عامر",
    "text": "I will not ask you to ever",
    "time": "Nov 16, 2024 12:55 am",
    "reactions": [],
    "kind": "msg"
  },
  {
    "sender": "Aamir | عامر",
    "text": "My brother lies and goes to place",
    "time": "Nov 16, 2024 12:55 am",
    "reactions": [],
    "kind": "msg"
  },
  {
    "sender": "Aamir | عامر",
    "text": "And it doesn’t end good on himSo I will say not to based on my experience",
    "time": "Nov 16, 2024 12:56 am",
    "reactions": [],
    "kind": "msg"
  },
  {
    "sender": "Bushra Khan",
    "text": "Okay 😔",
    "time": "Nov 16, 2024 12:56 am",
    "reactions": [],
    "kind": "msg"
  },
  {
    "sender": "Bushra Khan",
    "text": "I’ll tell her",
    "time": "Nov 16, 2024 12:56 am",
    "reactions": [],
    "kind": "msg"
  },
  {
    "sender": "Aamir | عامر",
    "text": "I am not liking this too 🥹",
    "time": "Nov 16, 2024 12:57 am",
    "reactions": [],
    "kind": "msg"
  },
  {
    "sender": "Bushra Khan",
    "text": "I know",
    "time": "Nov 16, 2024 12:57 am",
    "reactions": [],
    "kind": "msg"
  },
  {
    "sender": "Bushra Khan",
    "text": "I was confused",
    "time": "Nov 16, 2024 12:57 am",
    "reactions": [],
    "kind": "msg"
  },
  {
    "sender": "Bushra Khan",
    "text": "So I asked you",
    "time": "Nov 16, 2024 12:57 am",
    "reactions": [],
    "kind": "msg"
  },
  {
    "sender": "Aamir | عامر",
    "text": "I am just waiting for the day I could take you to all the places and make you happy",
    "time": "Nov 16, 2024 12:58 am",
    "reactions": [
      {
        "reactor": "Bushra Khan",
        "emoji": "❤️"
      }
    ],
    "kind": "msg"
  },
  {
    "sender": "Bushra Khan",
    "text": "I am too",
    "time": "Nov 16, 2024 12:58 am",
    "reactions": [
      {
        "reactor": "Aamir | عامر",
        "emoji": "❤️"
      }
    ],
    "kind": "msg"
  },
  {
    "sender": "Bushra Khan",
    "text": "😤",
    "time": "Nov 16, 2024 12:58 am",
    "reactions": [
      {
        "reactor": "Aamir | عامر",
        "emoji": "❤️"
      }
    ],
    "kind": "msg"
  },
  {
    "sender": "Aamir | عامر",
    "text": "And we will have to never look back 😤",
    "time": "Nov 16, 2024 12:58 am",
    "reactions": [
      {
        "reactor": "Bushra Khan",
        "emoji": "❤️"
      }
    ],
    "kind": "msg"
  },
  {
    "sender": "Bushra Khan",
    "text": "Yepppp",
    "time": "Nov 16, 2024 12:59 am",
    "reactions": [
      {
        "reactor": "Aamir | عامر",
        "emoji": "❤️"
      }
    ],
    "kind": "msg"
  },
  {
    "sender": "Aamir | عامر",
    "text": "You know the first place I wanna take you to ma’am",
    "time": "Nov 16, 2024 12:59 am",
    "reactions": [],
    "kind": "msg"
  },
  {
    "sender": "Aamir | عامر",
    "text": "Not in here I mean other country",
    "time": "Nov 16, 2024 12:59 am",
    "reactions": [],
    "kind": "msg"
  },
  {
    "sender": "Bushra Khan",
    "text": "No sir",
    "time": "Nov 16, 2024 1:07 am",
    "reactions": [],
    "kind": "msg"
  },
  {
    "sender": "Bushra Khan",
    "text": "You tell me",
    "time": "Nov 16, 2024 1:08 am",
    "reactions": [],
    "kind": "msg"
  },
  {
    "sender": "Aamir | عامر",
    "text": "You sent an attachment.",
    "time": "Nov 16, 2024 1:09 am",
    "reactions": [
      {
        "reactor": "Bushra Khan",
        "emoji": "❤️"
      }
    ],
    "kind": "msg"
  },
  {
    "sender": "Bushra Khan",
    "text": "I was having food",
    "time": "Nov 16, 2024 1:22 am",
    "reactions": [
      {
        "reactor": "Aamir | عامر",
        "emoji": "❤️"
      }
    ],
    "kind": "msg"
  },
  {
    "sender": "Bushra Khan",
    "text": "Sorry",
    "time": "Nov 16, 2024 1:22 am",
    "reactions": [],
    "kind": "msg"
  },
  {
    "sender": "Bushra Khan",
    "text": "Yeepppp",
    "time": "Nov 16, 2024 1:22 am",
    "reactions": [
      {
        "reactor": "Aamir | عامر",
        "emoji": "❤️"
      }
    ],
    "kind": "msg"
  },
  {
    "sender": "Aamir | عامر",
    "text": "I just had lunch too",
    "time": "Nov 16, 2024 1:28 am",
    "reactions": [
      {
        "reactor": "Bushra Khan",
        "emoji": "❤️"
      }
    ],
    "kind": "msg"
  },
  {
    "sender": "Aamir | عامر",
    "text": "Kuch nahi tha",
    "time": "Nov 16, 2024 1:28 am",
    "reactions": [],
    "kind": "msg"
  },
  {
    "sender": "Aamir | عامر",
    "text": "Daal chawal sirf",
    "time": "Nov 16, 2024 1:28 am",
    "reactions": [
      {
        "reactor": "Bushra Khan",
        "emoji": "😢"
      }
    ],
    "kind": "msg"
  },
  {
    "sender": "Aamir | عامر",
    "text": "Ammi Ghar pe nahi hai",
    "time": "Nov 16, 2024 1:29 am",
    "reactions": [],
    "kind": "msg"
  },
  {
    "sender": "Bushra Khan",
    "text": "Eggs would have been good",
    "time": "Nov 16, 2024 1:29 am",
    "reactions": [
      {
        "reactor": "Aamir | عامر",
        "emoji": "❤️"
      }
    ],
    "kind": "msg"
  },
  {
    "sender": "Aamir | عامر",
    "text": "I totally forgot 😫",
    "time": "Nov 16, 2024 1:30 am",
    "reactions": [],
    "kind": "msg"
  },
  {
    "sender": "Bushra Khan",
    "text": "The eggs ?",
    "time": "Nov 16, 2024 1:30 am",
    "reactions": [],
    "kind": "msg"
  },
  {
    "sender": "Aamir | عامر",
    "text": "Yuppp",
    "time": "Nov 16, 2024 1:30 am",
    "reactions": [],
    "kind": "msg"
  },
  {
    "sender": "Bushra Khan",
    "text": "It’s okay 😁",
    "time": "Nov 16, 2024 1:30 am",
    "reactions": [],
    "kind": "msg"
  },
  {
    "sender": "Aamir | عامر",
    "text": "Okay ma’am",
    "time": "Nov 16, 2024 1:30 am",
    "reactions": [],
    "kind": "msg"
  },
  {
    "sender": "Aamir | عامر",
    "text": "She won’t come in night too",
    "time": "Nov 16, 2024 1:31 am",
    "reactions": [],
    "kind": "msg"
  },
  {
    "sender": "Bushra Khan",
    "text": "Ohhh",
    "time": "Nov 16, 2024 1:31 am",
    "reactions": [],
    "kind": "msg"
  },
  {
    "sender": "Aamir | عامر",
    "text": "Went to Mira Road, mama k Ghar",
    "time": "Nov 16, 2024 1:31 am",
    "reactions": [
      {
        "reactor": "Bushra Khan",
        "emoji": "❤️"
      }
    ],
    "kind": "msg"
  },
  {
    "sender": "Aamir | عامر",
    "text": "Yupp",
    "time": "Nov 16, 2024 1:31 am",
    "reactions": [],
    "kind": "msg"
  },
  {
    "sender": "Aamir | عامر",
    "text": "Will have to make something for night 🥲",
    "time": "Nov 16, 2024 1:31 am",
    "reactions": [],
    "kind": "msg"
  },
  {
    "sender": "Bushra Khan",
    "text": "What will you make ?",
    "time": "Nov 16, 2024 1:32 am",
    "reactions": [],
    "kind": "msg"
  },
  {
    "sender": "Aamir | عامر",
    "text": "Pata nahi",
    "time": "Nov 16, 2024 1:32 am",
    "reactions": [],
    "kind": "msg"
  },
  {
    "sender": "Aamir | عامر",
    "text": "Sochna paddega",
    "time": "Nov 16, 2024 1:32 am",
    "reactions": [],
    "kind": "msg"
  },
  {
    "sender": "Bushra Khan",
    "text": "Okayy",
    "time": "Nov 16, 2024 1:33 am",
    "reactions": [],
    "kind": "msg"
  },
  {
    "sender": "Aamir | عامر",
    "text": "Or will come to your home 😁",
    "time": "Nov 16, 2024 1:33 am",
    "reactions": [
      {
        "reactor": "Bushra Khan",
        "emoji": "❤️"
      }
    ],
    "kind": "msg"
  },
  {
    "sender": "Aamir | عامر",
    "text": "Just said for manifesting",
    "time": "Nov 16, 2024 1:34 am",
    "reactions": [],
    "kind": "msg"
  },
  {
    "sender": "Aamir | عامر",
    "text": "Ma’am",
    "time": "Nov 16, 2024 1:35 am",
    "reactions": [],
    "kind": "msg"
  },
  {
    "sender": "Aamir | عامر",
    "text": "Wanna play",
    "time": "Nov 16, 2024 1:35 am",
    "reactions": [],
    "kind": "msg"
  },
  {
    "sender": "Bushra Khan",
    "text": "😁 Okayy",
    "time": "Nov 16, 2024 1:35 am",
    "reactions": [
      {
        "reactor": "Aamir | عامر",
        "emoji": "❤️"
      }
    ],
    "kind": "msg"
  },
  {
    "sender": "Bushra Khan",
    "text": "Yep",
    "time": "Nov 16, 2024 1:35 am",
    "reactions": [
      {
        "reactor": "Aamir | عامر",
        "emoji": "❤️"
      }
    ],
    "kind": "msg"
  },
  {
    "sender": "Aamir | عامر",
    "text": "Noice 😁",
    "time": "Nov 16, 2024 1:45 am",
    "reactions": [
      {
        "reactor": "Bushra Khan",
        "emoji": "❤️"
      }
    ],
    "kind": "msg"
  },
  {
    "sender": "Bushra Khan",
    "text": "Paint",
    "time": "Nov 16, 2024 1:45 am",
    "reactions": [],
    "kind": "msg"
  },
  {
    "sender": "Aamir | عامر",
    "text": "Okay ☠️",
    "time": "Nov 16, 2024 1:46 am",
    "reactions": [],
    "kind": "msg"
  },
  {
    "sender": "Aamir | عامر",
    "text": "🙄",
    "time": "Nov 16, 2024 1:46 am",
    "reactions": [],
    "kind": "msg"
  },
  {
    "sender": "Bushra Khan",
    "text": "What happened sir",
    "time": "Nov 16, 2024 1:47 am",
    "reactions": [],
    "kind": "msg"
  },
  {
    "sender": "Aamir | عامر",
    "text": "How did you know",
    "time": "Nov 16, 2024 1:47 am",
    "reactions": [],
    "kind": "msg"
  },
  {
    "sender": "Bushra Khan",
    "text": "Hehe",
    "time": "Nov 16, 2024 1:47 am",
    "reactions": [
      {
        "reactor": "Aamir | عامر",
        "emoji": "❤️"
      }
    ],
    "kind": "msg"
  },
  {
    "sender": "Bushra Khan",
    "text": "Noice",
    "time": "Nov 16, 2024 1:53 am",
    "reactions": [],
    "kind": "msg"
  },
  {
    "sender": "Aamir | عامر",
    "text": "😮",
    "time": "Nov 16, 2024 1:53 am",
    "reactions": [],
    "kind": "msg"
  },
  {
    "sender": "Aamir | عامر",
    "text": "Keeping up with you 😁",
    "time": "Nov 16, 2024 1:53 am",
    "reactions": [],
    "kind": "msg"
  },
  {
    "sender": "Aamir | عامر",
    "text": "Trying to",
    "time": "Nov 16, 2024 1:53 am",
    "reactions": [],
    "kind": "msg"
  },
  {
    "sender": "Aamir | عامر",
    "text": "You good at this",
    "time": "Nov 16, 2024 1:54 am",
    "reactions": [],
    "kind": "msg"
  },
  {
    "sender": "Aamir | عامر",
    "text": "Magician",
    "time": "Nov 16, 2024 1:54 am",
    "reactions": [
      {
        "reactor": "Bushra Khan",
        "emoji": "❤️"
      }
    ],
    "kind": "msg"
  },
  {
    "sender": "Bushra Khan",
    "text": "You are better",
    "time": "Nov 16, 2024 1:54 am",
    "reactions": [],
    "kind": "msg"
  },
  {
    "sender": "Aamir | عامر",
    "text": "Naah",
    "time": "Nov 16, 2024 1:54 am",
    "reactions": [],
    "kind": "msg"
  },
  {
    "sender": "Aamir | عامر",
    "text": "I was",
    "time": "Nov 16, 2024 1:54 am",
    "reactions": [],
    "kind": "msg"
  },
  {
    "sender": "Aamir | عامر",
    "text": "Not you are much better",
    "time": "Nov 16, 2024 1:54 am",
    "reactions": [
      {
        "reactor": "Bushra Khan",
        "emoji": "❤️"
      }
    ],
    "kind": "msg"
  },
  {
    "sender": "Aamir | عامر",
    "text": "Now you are much better (edited)",
    "time": "Nov 16, 2024 1:54 am",
    "reactions": [
      {
        "reactor": "Bushra Khan",
        "emoji": "❤️"
      }
    ],
    "kind": "msg"
  },
  {
    "sender": "Bushra Khan",
    "text": "They keep calling",
    "time": "Nov 16, 2024 1:57 am",
    "reactions": [],
    "kind": "msg"
  },
  {
    "sender": "Aamir | عامر",
    "text": "Okkayy",
    "time": "Nov 16, 2024 1:57 am",
    "reactions": [],
    "kind": "msg"
  },
  {
    "sender": "Aamir | عامر",
    "text": "What did you say",
    "time": "Nov 16, 2024 1:58 am",
    "reactions": [],
    "kind": "msg"
  },
  {
    "sender": "Bushra Khan",
    "text": "I told I can’t",
    "time": "Nov 16, 2024 1:58 am",
    "reactions": [],
    "kind": "msg"
  },
  {
    "sender": "Aamir | عامر",
    "text": "They do ask many times",
    "time": "Nov 16, 2024 2:01 am",
    "reactions": [],
    "kind": "msg"
  },
  {
    "sender": "Bushra Khan",
    "text": "Yepp",
    "time": "Nov 16, 2024 2:08 am",
    "reactions": [],
    "kind": "msg"
  },
  {
    "sender": "Aamir | عامر",
    "text": "You know",
    "time": "Nov 16, 2024 2:12 am",
    "reactions": [],
    "kind": "msg"
  },
  {
    "sender": "Aamir | عامر",
    "text": "There was this some movie which I thought we will watch",
    "time": "Nov 16, 2024 2:12 am",
    "reactions": [],
    "kind": "msg"
  },
  {
    "sender": "Aamir | عامر",
    "text": "But I forgot the name and can’t remember it now",
    "time": "Nov 16, 2024 2:12 am",
    "reactions": [],
    "kind": "msg"
  },
  {
    "sender": "Bushra Khan",
    "text": "😶",
    "time": "Nov 16, 2024 2:14 am",
    "reactions": [],
    "kind": "msg"
  },
  {
    "sender": "Bushra Khan",
    "text": "It’s okay",
    "time": "Nov 16, 2024 2:14 am",
    "reactions": [],
    "kind": "msg"
  },
  {
    "sender": "Bushra Khan",
    "text": "Yaad aa jayega",
    "time": "Nov 16, 2024 2:15 am",
    "reactions": [],
    "kind": "msg"
  },
  {
    "sender": "Aamir | عامر",
    "text": "Nahi aaya to you gonna suggestWill watch that 😁",
    "time": "Nov 16, 2024 2:15 am",
    "reactions": [],
    "kind": "msg"
  },
  {
    "sender": "Bushra Khan",
    "text": "🤦🏻‍♀️",
    "time": "Nov 16, 2024 2:15 am",
    "reactions": [],
    "kind": "msg"
  },
  {
    "sender": "Bushra Khan",
    "text": "Yeh Galat hai",
    "time": "Nov 16, 2024 2:16 am",
    "reactions": [],
    "kind": "msg"
  },
  {
    "sender": "Aamir | عامر",
    "text": "KyuYou suggest good movies only 🙂‍↕️",
    "time": "Nov 16, 2024 2:16 am",
    "reactions": [],
    "kind": "msg"
  },
  {
    "sender": "Bushra Khan",
    "text": "Okay",
    "time": "Nov 16, 2024 2:18 am",
    "reactions": [],
    "kind": "msg"
  },
  {
    "sender": "Bushra Khan",
    "text": "I will find one",
    "time": "Nov 16, 2024 2:18 am",
    "reactions": [
      {
        "reactor": "Aamir | عامر",
        "emoji": "❤️"
      }
    ],
    "kind": "msg"
  },
  {
    "sender": "Aamir | عامر",
    "text": "Cool",
    "time": "Nov 16, 2024 2:18 am",
    "reactions": [],
    "kind": "msg"
  },
  {
    "sender": "Aamir | عامر",
    "text": "Meko Neend aa Rahi hai",
    "time": "Nov 16, 2024 2:18 am",
    "reactions": [
      {
        "reactor": "Bushra Khan",
        "emoji": "❤️"
      }
    ],
    "kind": "msg"
  },
  {
    "sender": "Bushra Khan",
    "text": "You woke up early",
    "time": "Nov 16, 2024 2:20 am",
    "reactions": [],
    "kind": "msg"
  },
  {
    "sender": "Bushra Khan",
    "text": "So jao",
    "time": "Nov 16, 2024 2:20 am",
    "reactions": [],
    "kind": "msg"
  },
  {
    "sender": "Aamir | عامر",
    "text": "Uthaogi Mujhe",
    "time": "Nov 16, 2024 2:21 am",
    "reactions": [],
    "kind": "msg"
  },
  {
    "sender": "Bushra Khan",
    "text": "Jiii",
    "time": "Nov 16, 2024 2:21 am",
    "reactions": [],
    "kind": "msg"
  },
  {
    "sender": "Bushra Khan",
    "text": "Kab ?",
    "time": "Nov 16, 2024 2:21 am",
    "reactions": [],
    "kind": "msg"
  },
  {
    "sender": "Aamir | عامر",
    "text": "You wanna sleep too ma’am?",
    "time": "Nov 16, 2024 2:21 am",
    "reactions": [],
    "kind": "msg"
  },
  {
    "sender": "Bushra Khan",
    "text": "I am not too sleepy",
    "time": "Nov 16, 2024 2:21 am",
    "reactions": [],
    "kind": "msg"
  },
  {
    "sender": "Bushra Khan",
    "text": "I’ll watch my dramas",
    "time": "Nov 16, 2024 2:21 am",
    "reactions": [],
    "kind": "msg"
  },
  {
    "sender": "Bushra Khan",
    "text": "😁",
    "time": "Nov 16, 2024 2:21 am",
    "reactions": [],
    "kind": "msg"
  },
  {
    "sender": "Aamir | عامر",
    "text": "Okkay 😁",
    "time": "Nov 16, 2024 2:21 am",
    "reactions": [
      {
        "reactor": "Bushra Khan",
        "emoji": "❤️"
      }
    ],
    "kind": "msg"
  },
  {
    "sender": "Bushra Khan",
    "text": "Then I’ll wake you",
    "time": "Nov 16, 2024 2:22 am",
    "reactions": [],
    "kind": "msg"
  },
  {
    "sender": "Aamir | عامر",
    "text": "6-6:30 k beech jab bhi man Kare",
    "time": "Nov 16, 2024 2:22 am",
    "reactions": [
      {
        "reactor": "Bushra Khan",
        "emoji": "❤️"
      }
    ],
    "kind": "msg"
  },
  {
    "sender": "Bushra Khan",
    "text": "Theek",
    "time": "Nov 16, 2024 2:23 am",
    "reactions": [],
    "kind": "msg"
  },
  {
    "sender": "Bushra Khan",
    "text": "Ab sojao",
    "time": "Nov 16, 2024 2:23 am",
    "reactions": [],
    "kind": "msg"
  },
  {
    "sender": "Aamir | عامر",
    "text": "Okay Hana 😴",
    "time": "Nov 16, 2024 2:23 am",
    "reactions": [
      {
        "reactor": "Bushra Khan",
        "emoji": "❤️"
      }
    ],
    "kind": "msg"
  },
  {
    "sender": "Bushra Khan",
    "text": "👋♥️♥️♥️",
    "time": "Nov 16, 2024 2:24 am",
    "reactions": [
      {
        "reactor": "Aamir | عامر",
        "emoji": "❤️"
      }
    ],
    "kind": "msg"
  },
  {
    "sender": "Aamir | عامر",
    "text": "❤️❤️❤️👋",
    "time": "Nov 16, 2024 2:25 am",
    "reactions": [
      {
        "reactor": "Bushra Khan",
        "emoji": "❤️"
      }
    ],
    "kind": "msg"
  },
  {
    "sender": "Aamir | عامر",
    "text": "Thank you",
    "time": "Nov 16, 2024 4:55 am",
    "reactions": [
      {
        "reactor": "Bushra Khan",
        "emoji": "❤️"
      }
    ],
    "kind": "msg"
  },
  {
    "sender": "Bushra Khan",
    "text": "😁",
    "time": "Nov 16, 2024 4:56 am",
    "reactions": [
      {
        "reactor": "Aamir | عامر",
        "emoji": "❤️"
      }
    ],
    "kind": "msg"
  },
  {
    "sender": "Aamir | عامر",
    "text": "Kya kar Rahi ho",
    "time": "Nov 16, 2024 6:34 am",
    "reactions": [],
    "kind": "msg"
  },
  {
    "sender": "Bushra Khan",
    "text": "Was talking to a friend",
    "time": "Nov 16, 2024 6:35 am",
    "reactions": [],
    "kind": "msg"
  },
  {
    "sender": "Aamir | عامر",
    "text": "Okay ma’am",
    "time": "Nov 16, 2024 6:35 am",
    "reactions": [],
    "kind": "msg"
  },
  {
    "sender": "Aamir | عامر",
    "text": "There is no one at home",
    "time": "Nov 16, 2024 6:36 am",
    "reactions": [],
    "kind": "msg"
  },
  {
    "sender": "Bushra Khan",
    "text": "Did you eat something",
    "time": "Nov 16, 2024 6:36 am",
    "reactions": [],
    "kind": "msg"
  },
  {
    "sender": "Aamir | عامر",
    "text": "Not yet",
    "time": "Nov 16, 2024 6:36 am",
    "reactions": [],
    "kind": "msg"
  },
  {
    "sender": "Bushra Khan",
    "text": "You must be hungry",
    "time": "Nov 16, 2024 6:36 am",
    "reactions": [],
    "kind": "msg"
  },
  {
    "sender": "Aamir | عامر",
    "text": "A bit",
    "time": "Nov 16, 2024 6:37 am",
    "reactions": [],
    "kind": "msg"
  },
  {
    "sender": "Aamir | عامر",
    "text": "And I am bored",
    "time": "Nov 16, 2024 6:37 am",
    "reactions": [
      {
        "reactor": "Bushra Khan",
        "emoji": "😁"
      }
    ],
    "kind": "msg"
  },
  {
    "sender": "Aamir | عامر",
    "text": "I was able to loot these",
    "time": "Nov 16, 2024 6:41 am",
    "reactions": [],
    "kind": "msg"
  },
  {
    "sender": "Bushra Khan",
    "text": "😮",
    "time": "Nov 16, 2024 6:41 am",
    "reactions": [],
    "kind": "msg"
  },
  {
    "sender": "Aamir | عامر",
    "text": "😂",
    "time": "Nov 16, 2024 6:41 am",
    "reactions": [
      {
        "reactor": "Bushra Khan",
        "emoji": "❤️"
      }
    ],
    "kind": "msg"
  },
  {
    "sender": "Bushra Khan",
    "text": "Noiceee",
    "time": "Nov 16, 2024 6:41 am",
    "reactions": [],
    "kind": "msg"
  },
  {
    "sender": "Aamir | عامر",
    "text": "They have toblerone too and many other which we don’t get India",
    "time": "Nov 16, 2024 6:41 am",
    "reactions": [
      {
        "reactor": "Bushra Khan",
        "emoji": "❤️"
      }
    ],
    "kind": "msg"
  },
  {
    "sender": "Bushra Khan",
    "text": "Rightt",
    "time": "Nov 16, 2024 6:41 am",
    "reactions": [],
    "kind": "msg"
  },
  {
    "sender": "Aamir | عامر",
    "text": "When the town hall was going on my manager went away and took all from the display 😂",
    "time": "Nov 16, 2024 6:42 am",
    "reactions": [
      {
        "reactor": "Bushra Khan",
        "emoji": "😂"
      }
    ],
    "kind": "msg"
  },
  {
    "sender": "Bushra Khan",
    "text": "The manager ?",
    "time": "Nov 16, 2024 6:42 am",
    "reactions": [],
    "kind": "msg"
  },
  {
    "sender": "Aamir | عامر",
    "text": "Yuppp",
    "time": "Nov 16, 2024 6:42 am",
    "reactions": [],
    "kind": "msg"
  },
  {
    "sender": "Aamir | عامر",
    "text": "They all become shameless",
    "time": "Nov 16, 2024 6:42 am",
    "reactions": [
      {
        "reactor": "Bushra Khan",
        "emoji": "😂"
      }
    ],
    "kind": "msg"
  },
  {
    "sender": "Aamir | عامر",
    "text": "😂",
    "time": "Nov 16, 2024 6:42 am",
    "reactions": [],
    "kind": "msg"
  },
  {
    "sender": "Aamir | عامر",
    "text": "Next time I will make a video and send",
    "time": "Nov 16, 2024 6:42 am",
    "reactions": [
      {
        "reactor": "Bushra Khan",
        "emoji": "❤️"
      }
    ],
    "kind": "msg"
  },
  {
    "sender": "Bushra Khan",
    "text": "Yepp",
    "time": "Nov 16, 2024 6:43 am",
    "reactions": [],
    "kind": "msg"
  },
  {
    "sender": "Bushra Khan",
    "text": "I was going to ask",
    "time": "Nov 16, 2024 6:43 am",
    "reactions": [],
    "kind": "msg"
  },
  {
    "sender": "Aamir | عامر",
    "text": "That’s too chaotic and funny 🤣",
    "time": "Nov 16, 2024 6:43 am",
    "reactions": [
      {
        "reactor": "Bushra Khan",
        "emoji": "❤️"
      }
    ],
    "kind": "msg"
  },
  {
    "sender": "Aamir | عامر",
    "text": "I will send you a personalised Cadbury, with your picture on the wrapper 😁",
    "time": "Nov 16, 2024 6:44 am",
    "reactions": [],
    "kind": "msg"
  },
  {
    "sender": "Bushra Khan",
    "text": "🫢😁",
    "time": "Nov 16, 2024 6:44 am",
    "reactions": [],
    "kind": "msg"
  },
  {
    "sender": "Bushra Khan",
    "text": "That would be interesting",
    "time": "Nov 16, 2024 6:44 am",
    "reactions": [
      {
        "reactor": "Aamir | عامر",
        "emoji": "❤️"
      }
    ],
    "kind": "msg"
  },
  {
    "sender": "Aamir | عامر",
    "text": "Yupp, will send",
    "time": "Nov 16, 2024 6:44 am",
    "reactions": [
      {
        "reactor": "Bushra Khan",
        "emoji": "❤️"
      }
    ],
    "kind": "msg"
  },
  {
    "sender": "Bushra Khan",
    "text": "I’ll keep it framed 😁",
    "time": "Nov 16, 2024 6:45 am",
    "reactions": [
      {
        "reactor": "Aamir | عامر",
        "emoji": "❤️"
      }
    ],
    "kind": "msg"
  },
  {
    "sender": "Aamir | عامر",
    "text": "Hehe, cool",
    "time": "Nov 16, 2024 6:45 am",
    "reactions": [
      {
        "reactor": "Bushra Khan",
        "emoji": "❤️"
      }
    ],
    "kind": "msg"
  },
  {
    "sender": "Bushra Khan",
    "text": "Yepppp",
    "time": "Nov 16, 2024 6:46 am",
    "reactions": [],
    "kind": "msg"
  },
  {
    "sender": "Aamir | عامر",
    "text": "Saurabh is my manager",
    "time": "Nov 16, 2024 6:47 am",
    "reactions": [],
    "kind": "msg"
  },
  {
    "sender": "Aamir | عامر",
    "text": "And he reached in the morning",
    "time": "Nov 16, 2024 6:47 am",
    "reactions": [
      {
        "reactor": "Bushra Khan",
        "emoji": "😮"
      }
    ],
    "kind": "msg"
  },
  {
    "sender": "Aamir | عامر",
    "text": "Was too drunk 😂",
    "time": "Nov 16, 2024 6:47 am",
    "reactions": [],
    "kind": "msg"
  },
  {
    "sender": "Bushra Khan",
    "text": "😶😂",
    "time": "Nov 16, 2024 6:47 am",
    "reactions": [],
    "kind": "msg"
  },
  {
    "sender": "Aamir | عامر",
    "text": "😂😂",
    "time": "Nov 16, 2024 6:48 am",
    "reactions": [
      {
        "reactor": "Bushra Khan",
        "emoji": "❤️"
      }
    ],
    "kind": "msg"
  }
]