[
  {
    "sender": "Aamir | عامر",
    "text": "What she sent",
    "time": "Mar 04, 2025 5:04 am",
    "reactions": [],
    "kind": "msg"
  },
  {
    "sender": "Bushra Khan",
    "text": "Bhajiya",
    "time": "Mar 04, 2025 5:04 am",
    "reactions": [
      {
        "reactor": "Aamir | عامر",
        "emoji": "❤️"
      }
    ],
    "kind": "msg"
  },
  {
    "sender": "Aamir | عامر",
    "text": "Noice",
    "time": "Mar 04, 2025 5:04 am",
    "reactions": [
      {
        "reactor": "Bushra Khan",
        "emoji": "❤️"
      }
    ],
    "kind": "msg"
  },
  {
    "sender": "Aamir | عامر",
    "text": "You sent an attachment.",
    "time": "Mar 04, 2025 5:27 am",
    "reactions": [
      {
        "reactor": "Bushra Khan",
        "emoji": "❤️"
      }
    ],
    "kind": "msg"
  },
  {
    "sender": "Aamir | عامر",
    "text": "Abhi rickshaw mili",
    "time": "Mar 04, 2025 6:37 am",
    "reactions": [
      {
        "reactor": "Bushra Khan",
        "emoji": "❤️"
      }
    ],
    "kind": "msg"
  },
  {
    "sender": "Bushra Khan",
    "text": "Okayyy",
    "time": "Mar 04, 2025 6:38 am",
    "reactions": [
      {
        "reactor": "Aamir | عامر",
        "emoji": "❤️"
      }
    ],
    "kind": "msg"
  },
  {
    "sender": "Aamir | عامر",
    "text": "Reached hime ma’am",
    "time": "Mar 04, 2025 7:09 am",
    "reactions": [
      {
        "reactor": "Bushra Khan",
        "emoji": "❤️"
      }
    ],
    "kind": "msg"
  },
  {
    "sender": "Bushra Khan",
    "text": "Okay sir",
    "time": "Mar 04, 2025 7:09 am",
    "reactions": [
      {
        "reactor": "Aamir | عامر",
        "emoji": "❤️"
      }
    ],
    "kind": "msg"
  },
  {
    "sender": "Aamir | عامر",
    "text": "Its so hot 🥲",
    "time": "Mar 04, 2025 7:10 am",
    "reactions": [],
    "kind": "msg"
  },
  {
    "sender": "Bushra Khan",
    "text": "Yepp 😁",
    "time": "Mar 04, 2025 7:10 am",
    "reactions": [],
    "kind": "msg"
  },
  {
    "sender": "Aamir | عامر",
    "text": "😔",
    "time": "Mar 04, 2025 8:28 am",
    "reactions": [],
    "kind": "msg"
  },
  {
    "sender": "Aamir | عامر",
    "text": "My phone got off",
    "time": "Mar 04, 2025 8:28 am",
    "reactions": [],
    "kind": "msg"
  },
  {
    "sender": "Aamir | عامر",
    "text": "I had dinner too",
    "time": "Mar 04, 2025 8:28 am",
    "reactions": [
      {
        "reactor": "Bushra Khan",
        "emoji": "❤️"
      }
    ],
    "kind": "msg"
  },
  {
    "sender": "Aamir | عامر",
    "text": "Was very hungry",
    "time": "Mar 04, 2025 8:28 am",
    "reactions": [],
    "kind": "msg"
  },
  {
    "sender": "Aamir | عامر",
    "text": "Did you eat ma’am",
    "time": "Mar 04, 2025 8:28 am",
    "reactions": [],
    "kind": "msg"
  },
  {
    "sender": "Aamir | عامر",
    "text": "You sent an attachment.",
    "time": "Mar 04, 2025 8:40 am",
    "reactions": [
      {
        "reactor": "Bushra Khan",
        "emoji": "❤️"
      }
    ],
    "kind": "msg"
  },
  {
    "sender": "Bushra Khan",
    "text": "I did",
    "time": "Mar 04, 2025 9:15 am",
    "reactions": [
      {
        "reactor": "Aamir | عامر",
        "emoji": "❤️"
      }
    ],
    "kind": "msg"
  },
  {
    "sender": "Bushra Khan",
    "text": "I had cauliflower Ki bhaaji",
    "time": "Mar 04, 2025 9:15 am",
    "reactions": [
      {
        "reactor": "Aamir | عامر",
        "emoji": "❤️"
      }
    ],
    "kind": "msg"
  },
  {
    "sender": "Aamir | عامر",
    "text": "Noice",
    "time": "Mar 04, 2025 9:17 am",
    "reactions": [
      {
        "reactor": "Bushra Khan",
        "emoji": "❤️"
      }
    ],
    "kind": "msg"
  },
  {
    "sender": "Aamir | عامر",
    "text": "I had roti and chicken",
    "time": "Mar 04, 2025 9:18 am",
    "reactions": [
      {
        "reactor": "Bushra Khan",
        "emoji": "❤️"
      }
    ],
    "kind": "msg"
  },
  {
    "sender": "Bushra Khan",
    "text": "Noice",
    "time": "Mar 04, 2025 9:26 am",
    "reactions": [
      {
        "reactor": "Aamir | عامر",
        "emoji": "❤️"
      }
    ],
    "kind": "msg"
  },
  {
    "sender": "Bushra Khan",
    "text": "Instagram user sent an attachment.",
    "time": "Mar 04, 2025 10:16 am",
    "reactions": [
      {
        "reactor": "Aamir | عامر",
        "emoji": "❤️"
      }
    ],
    "kind": "msg"
  },
  {
    "sender": "Aamir | عامر",
    "text": "The oscar goes to meownardo di caprio 😂",
    "time": "Mar 04, 2025 10:35 am",
    "reactions": [
      {
        "reactor": "Bushra Khan",
        "emoji": "😂"
      }
    ],
    "kind": "msg"
  },
  {
    "sender": "Bushra Khan",
    "text": "So nice of a cat",
    "time": "Mar 04, 2025 10:36 am",
    "reactions": [
      {
        "reactor": "Aamir | عامر",
        "emoji": "❤️"
      }
    ],
    "kind": "msg"
  },
  {
    "sender": "Aamir | عامر",
    "text": "Yuppp",
    "time": "Mar 04, 2025 10:37 am",
    "reactions": [],
    "kind": "msg"
  },
  {
    "sender": "Bushra Khan",
    "text": "It’s so pretttyyyy",
    "time": "Mar 04, 2025 10:39 am",
    "reactions": [
      {
        "reactor": "Aamir | عامر",
        "emoji": "❤️"
      }
    ],
    "kind": "msg"
  },
  {
    "sender": "Aamir | عامر",
    "text": "Made mow",
    "time": "Mar 04, 2025 10:39 am",
    "reactions": [],
    "kind": "msg"
  },
  {
    "sender": "Bushra Khan",
    "text": "😁",
    "time": "Mar 04, 2025 10:40 am",
    "reactions": [
      {
        "reactor": "Aamir | عامر",
        "emoji": "❤️"
      }
    ],
    "kind": "msg"
  },
  {
    "sender": "Bushra Khan",
    "text": "You are really good at it",
    "time": "Mar 04, 2025 10:40 am",
    "reactions": [
      {
        "reactor": "Aamir | عامر",
        "emoji": "❤️"
      }
    ],
    "kind": "msg"
  },
  {
    "sender": "Bushra Khan",
    "text": "😌",
    "time": "Mar 04, 2025 10:40 am",
    "reactions": [],
    "kind": "msg"
  },
  {
    "sender": "Aamir | عامر",
    "text": "😁 if you say",
    "time": "Mar 04, 2025 10:40 am",
    "reactions": [
      {
        "reactor": "Bushra Khan",
        "emoji": "❤️"
      }
    ],
    "kind": "msg"
  },
  {
    "sender": "Bushra Khan",
    "text": "Yepp",
    "time": "Mar 04, 2025 10:41 am",
    "reactions": [
      {
        "reactor": "Aamir | عامر",
        "emoji": "❤️"
      }
    ],
    "kind": "msg"
  },
  {
    "sender": "Aamir | عامر",
    "text": "Done with the work ma’am",
    "time": "Mar 04, 2025 10:58 am",
    "reactions": [],
    "kind": "msg"
  },
  {
    "sender": "Bushra Khan",
    "text": "Nope",
    "time": "Mar 04, 2025 10:59 am",
    "reactions": [],
    "kind": "msg"
  },
  {
    "sender": "Bushra Khan",
    "text": "Have 16 mins more",
    "time": "Mar 04, 2025 10:59 am",
    "reactions": [],
    "kind": "msg"
  },
  {
    "sender": "Aamir | عامر",
    "text": "Okay ma’am",
    "time": "Mar 04, 2025 11:00 am",
    "reactions": [],
    "kind": "msg"
  },
  {
    "sender": "Bushra Khan",
    "text": "Yep",
    "time": "Mar 04, 2025 11:01 am",
    "reactions": [
      {
        "reactor": "Aamir | عامر",
        "emoji": "❤️"
      }
    ],
    "kind": "msg"
  },
  {
    "sender": "Bushra Khan",
    "text": "Have logged out",
    "time": "Mar 04, 2025 11:30 am",
    "reactions": [
      {
        "reactor": "Aamir | عامر",
        "emoji": "❤️"
      }
    ],
    "kind": "msg"
  },
  {
    "sender": "Bushra Khan",
    "text": "Need to pray",
    "time": "Mar 04, 2025 11:30 am",
    "reactions": [
      {
        "reactor": "Aamir | عامر",
        "emoji": "❤️"
      }
    ],
    "kind": "msg"
  },
  {
    "sender": "Bushra Khan",
    "text": "You can sleep if you want sir",
    "time": "Mar 04, 2025 11:30 am",
    "reactions": [
      {
        "reactor": "Aamir | عامر",
        "emoji": "❤️"
      }
    ],
    "kind": "msg"
  },
  {
    "sender": "Aamir | عامر",
    "text": "Did you wake up for suhoor ma’am",
    "time": "Mar 04, 2025 3:38 pm",
    "reactions": [],
    "kind": "msg"
  },
  {
    "sender": "Aamir | عامر",
    "text": "Hana",
    "time": "Mar 04, 2025 3:42 pm",
    "reactions": [],
    "kind": "msg"
  },
  {
    "sender": "Aamir | عامر",
    "text": "I had suhoor",
    "time": "Mar 04, 2025 3:47 pm",
    "reactions": [
      {
        "reactor": "Bushra Khan",
        "emoji": "❤️"
      }
    ],
    "kind": "msg"
  },
  {
    "sender": "Aamir | عامر",
    "text": "Am really sorry, I fell asleep just after texting",
    "time": "Mar 04, 2025 3:52 pm",
    "reactions": [],
    "kind": "msg"
  },
  {
    "sender": "Bushra Khan",
    "text": "It’s okay",
    "time": "Mar 04, 2025 3:59 pm",
    "reactions": [],
    "kind": "msg"
  },
  {
    "sender": "Bushra Khan",
    "text": "I thought so",
    "time": "Mar 04, 2025 3:59 pm",
    "reactions": [],
    "kind": "msg"
  },
  {
    "sender": "Bushra Khan",
    "text": "I had tooo",
    "time": "Mar 04, 2025 3:59 pm",
    "reactions": [],
    "kind": "msg"
  },
  {
    "sender": "Bushra Khan",
    "text": "I had Kelloggs",
    "time": "Mar 04, 2025 3:59 pm",
    "reactions": [
      {
        "reactor": "Aamir | عامر",
        "emoji": "❤️"
      }
    ],
    "kind": "msg"
  },
  {
    "sender": "Aamir | عامر",
    "text": "It’s notI wanted to talk 😢",
    "time": "Mar 04, 2025 4:00 pm",
    "reactions": [],
    "kind": "msg"
  },
  {
    "sender": "Bushra Khan",
    "text": "But you had come travelling na",
    "time": "Mar 04, 2025 4:00 pm",
    "reactions": [],
    "kind": "msg"
  },
  {
    "sender": "Bushra Khan",
    "text": "So you would have been tired",
    "time": "Mar 04, 2025 4:00 pm",
    "reactions": [],
    "kind": "msg"
  },
  {
    "sender": "Bushra Khan",
    "text": "And the shift was late",
    "time": "Mar 04, 2025 4:00 pm",
    "reactions": [],
    "kind": "msg"
  },
  {
    "sender": "Aamir | عامر",
    "text": "Okay ma’amStill am sorry",
    "time": "Mar 04, 2025 4:01 pm",
    "reactions": [],
    "kind": "msg"
  },
  {
    "sender": "Aamir | عامر",
    "text": "Dod you have suhoor",
    "time": "Mar 04, 2025 4:01 pm",
    "reactions": [],
    "kind": "msg"
  },
  {
    "sender": "Bushra Khan",
    "text": "🙅‍♀️",
    "time": "Mar 04, 2025 4:01 pm",
    "reactions": [
      {
        "reactor": "Aamir | عامر",
        "emoji": "❤️"
      }
    ],
    "kind": "msg"
  },
  {
    "sender": "Bushra Khan",
    "text": "Yepp",
    "time": "Mar 04, 2025 4:01 pm",
    "reactions": [
      {
        "reactor": "Aamir | عامر",
        "emoji": "❤️"
      }
    ],
    "kind": "msg"
  },
  {
    "sender": "Aamir | عامر",
    "text": "Did you have suhoor (edited)",
    "time": "Mar 04, 2025 4:01 pm",
    "reactions": [],
    "kind": "msg"
  },
  {
    "sender": "Aamir | عامر",
    "text": "What did you have",
    "time": "Mar 04, 2025 4:01 pm",
    "reactions": [],
    "kind": "msg"
  },
  {
    "sender": "Bushra Khan",
    "text": ".",
    "time": "Mar 04, 2025 4:01 pm",
    "reactions": [],
    "kind": "msg"
  },
  {
    "sender": "Bushra Khan",
    "text": "What did you have",
    "time": "Mar 04, 2025 4:01 pm",
    "reactions": [],
    "kind": "msg"
  },
  {
    "sender": "Aamir | عامر",
    "text": "Had muesli",
    "time": "Mar 04, 2025 4:02 pm",
    "reactions": [
      {
        "reactor": "Bushra Khan",
        "emoji": "❤️"
      }
    ],
    "kind": "msg"
  },
  {
    "sender": "Bushra Khan",
    "text": "Healthy person",
    "time": "Mar 04, 2025 4:02 pm",
    "reactions": [],
    "kind": "msg"
  },
  {
    "sender": "Aamir | عامر",
    "text": "Wohi tha bas",
    "time": "Mar 04, 2025 4:02 pm",
    "reactions": [],
    "kind": "msg"
  },
  {
    "sender": "Bushra Khan",
    "text": "Theeke theeke",
    "time": "Mar 04, 2025 4:02 pm",
    "reactions": [],
    "kind": "msg"
  },
  {
    "sender": "Aamir | عامر",
    "text": "Man nahi ho raha tha khaane",
    "time": "Mar 04, 2025 4:02 pm",
    "reactions": [],
    "kind": "msg"
  },
  {
    "sender": "Aamir | عامر",
    "text": "😁",
    "time": "Mar 04, 2025 4:02 pm",
    "reactions": [
      {
        "reactor": "Bushra Khan",
        "emoji": "❤️"
      }
    ],
    "kind": "msg"
  },
  {
    "sender": "Bushra Khan",
    "text": "Q",
    "time": "Mar 04, 2025 4:03 pm",
    "reactions": [],
    "kind": "msg"
  },
  {
    "sender": "Bushra Khan",
    "text": "What did you yesterday",
    "time": "Mar 04, 2025 4:03 pm",
    "reactions": [],
    "kind": "msg"
  },
  {
    "sender": "Aamir | عامر",
    "text": "I didn’t kept roza yesterday",
    "time": "Mar 04, 2025 4:03 pm",
    "reactions": [],
    "kind": "msg"
  },
  {
    "sender": "Aamir | عامر",
    "text": "I didn’t keep roza yesterday (edited)",
    "time": "Mar 04, 2025 4:03 pm",
    "reactions": [],
    "kind": "msg"
  },
  {
    "sender": "Bushra Khan",
    "text": "For dinner",
    "time": "Mar 04, 2025 4:04 pm",
    "reactions": [],
    "kind": "msg"
  },
  {
    "sender": "Aamir | عامر",
    "text": "Roti and chicken",
    "time": "Mar 04, 2025 4:04 pm",
    "reactions": [],
    "kind": "msg"
  },
  {
    "sender": "Aamir | عامر",
    "text": "Was full",
    "time": "Mar 04, 2025 4:04 pm",
    "reactions": [
      {
        "reactor": "Bushra Khan",
        "emoji": "❤️"
      }
    ],
    "kind": "msg"
  },
  {
    "sender": "Bushra Khan",
    "text": "It feels different after having bahar ka khana",
    "time": "Mar 04, 2025 4:05 pm",
    "reactions": [],
    "kind": "msg"
  },
  {
    "sender": "Aamir | عامر",
    "text": "Right it does",
    "time": "Mar 04, 2025 4:05 pm",
    "reactions": [
      {
        "reactor": "Bushra Khan",
        "emoji": "❤️"
      }
    ],
    "kind": "msg"
  },
  {
    "sender": "Aamir | عامر",
    "text": "I was just having veg stuff except last 2 days",
    "time": "Mar 04, 2025 4:05 pm",
    "reactions": [],
    "kind": "msg"
  },
  {
    "sender": "Bushra Khan",
    "text": "Rightttt",
    "time": "Mar 04, 2025 4:06 pm",
    "reactions": [],
    "kind": "msg"
  },
  {
    "sender": "Aamir | عامر",
    "text": "Paani piya aapne",
    "time": "Mar 04, 2025 4:06 pm",
    "reactions": [],
    "kind": "msg"
  },
  {
    "sender": "Bushra Khan",
    "text": "Haaa",
    "time": "Mar 04, 2025 4:06 pm",
    "reactions": [
      {
        "reactor": "Aamir | عامر",
        "emoji": "❤️"
      }
    ],
    "kind": "msg"
  },
  {
    "sender": "Aamir | عامر",
    "text": "Good",
    "time": "Mar 04, 2025 4:06 pm",
    "reactions": [
      {
        "reactor": "Bushra Khan",
        "emoji": "❤️"
      }
    ],
    "kind": "msg"
  },
  {
    "sender": "Bushra Khan",
    "text": "Aapne ?",
    "time": "Mar 04, 2025 4:07 pm",
    "reactions": [],
    "kind": "msg"
  },
  {
    "sender": "Aamir | عامر",
    "text": "Ji",
    "time": "Mar 04, 2025 4:07 pm",
    "reactions": [
      {
        "reactor": "Bushra Khan",
        "emoji": "❤️"
      }
    ],
    "kind": "msg"
  },
  {
    "sender": "Bushra Khan",
    "text": "Okayyy",
    "time": "Mar 04, 2025 4:07 pm",
    "reactions": [],
    "kind": "msg"
  },
  {
    "sender": "Bushra Khan",
    "text": "What will you do",
    "time": "Mar 04, 2025 4:07 pm",
    "reactions": [],
    "kind": "msg"
  },
  {
    "sender": "Bushra Khan",
    "text": "Now",
    "time": "Mar 04, 2025 4:07 pm",
    "reactions": [],
    "kind": "msg"
  },
  {
    "sender": "Aamir | عامر",
    "text": "Should I sleep",
    "time": "Mar 04, 2025 4:08 pm",
    "reactions": [],
    "kind": "msg"
  },
  {
    "sender": "Bushra Khan",
    "text": "If you want to",
    "time": "Mar 04, 2025 4:09 pm",
    "reactions": [],
    "kind": "msg"
  },
  {
    "sender": "Bushra Khan",
    "text": "You should",
    "time": "Mar 04, 2025 4:09 pm",
    "reactions": [],
    "kind": "msg"
  },
  {
    "sender": "Aamir | عامر",
    "text": "What will you ma’am",
    "time": "Mar 04, 2025 4:10 pm",
    "reactions": [],
    "kind": "msg"
  },
  {
    "sender": "Bushra Khan",
    "text": "I’ll sleep too",
    "time": "Mar 04, 2025 4:10 pm",
    "reactions": [],
    "kind": "msg"
  },
  {
    "sender": "Bushra Khan",
    "text": "After Azam",
    "time": "Mar 04, 2025 4:10 pm",
    "reactions": [],
    "kind": "msg"
  },
  {
    "sender": "Aamir | عامر",
    "text": "Okay ma’am",
    "time": "Mar 04, 2025 4:10 pm",
    "reactions": [],
    "kind": "msg"
  },
  {
    "sender": "Aamir | عامر",
    "text": "Today the work is at 3?",
    "time": "Mar 04, 2025 4:11 pm",
    "reactions": [],
    "kind": "msg"
  },
  {
    "sender": "Bushra Khan",
    "text": "Yepp",
    "time": "Mar 04, 2025 4:11 pm",
    "reactions": [],
    "kind": "msg"
  },
  {
    "sender": "Aamir | عامر",
    "text": "Okay ma’am",
    "time": "Mar 04, 2025 4:12 pm",
    "reactions": [],
    "kind": "msg"
  },
  {
    "sender": "Aamir | عامر",
    "text": "You sent an attachment.",
    "time": "Mar 04, 2025 4:14 pm",
    "reactions": [
      {
        "reactor": "Bushra Khan",
        "emoji": "❤️"
      }
    ],
    "kind": "msg"
  },
  {
    "sender": "Aamir | عامر",
    "text": "Will sleep ma’am okay",
    "time": "Mar 04, 2025 4:19 pm",
    "reactions": [
      {
        "reactor": "Bushra Khan",
        "emoji": "❤️"
      }
    ],
    "kind": "msg"
  },
  {
    "sender": "Aamir | عامر",
    "text": "You sleep soon too",
    "time": "Mar 04, 2025 4:20 pm",
    "reactions": [
      {
        "reactor": "Bushra Khan",
        "emoji": "❤️"
      }
    ],
    "kind": "msg"
  },
  {
    "sender": "Aamir | عامر",
    "text": "Allah hafiz",
    "time": "Mar 04, 2025 4:20 pm",
    "reactions": [
      {
        "reactor": "Bushra Khan",
        "emoji": "❤️"
      }
    ],
    "kind": "msg"
  },
  {
    "sender": "Aamir | عامر",
    "text": "👋❤️❤️❤️",
    "time": "Mar 04, 2025 4:20 pm",
    "reactions": [
      {
        "reactor": "Bushra Khan",
        "emoji": "❤️"
      }
    ],
    "kind": "msg"
  },
  {
    "sender": "Bushra Khan",
    "text": "Yeppp",
    "time": "Mar 04, 2025 4:26 pm",
    "reactions": [
      {
        "reactor": "Aamir | عامر",
        "emoji": "❤️"
      }
    ],
    "kind": "msg"
  },
  {
    "sender": "Bushra Khan",
    "text": "Allah hafiz",
    "time": "Mar 04, 2025 4:26 pm",
    "reactions": [
      {
        "reactor": "Aamir | عامر",
        "emoji": "❤️"
      }
    ],
    "kind": "msg"
  },
  {
    "sender": "Bushra Khan",
    "text": "👋💕💕💕",
    "time": "Mar 04, 2025 4:26 pm",
    "reactions": [
      {
        "reactor": "Aamir | عامر",
        "emoji": "❤️"
      }
    ],
    "kind": "msg"
  },
  {
    "sender": "Aamir | عامر",
    "text": "You sent an attachment.",
    "time": "Mar 04, 2025 7:43 pm",
    "reactions": [
      {
        "reactor": "Bushra Khan",
        "emoji": "❤️"
      }
    ],
    "kind": "msg"
  },
  {
    "sender": "Aamir | عامر",
    "text": "Did you read Quraan ma’am",
    "time": "Mar 05, 2025 12:57 am",
    "reactions": [],
    "kind": "msg"
  },
  {
    "sender": "Bushra Khan",
    "text": "Yepp done",
    "time": "Mar 05, 2025 1:00 am",
    "reactions": [
      {
        "reactor": "Aamir | عامر",
        "emoji": "❤️"
      }
    ],
    "kind": "msg"
  },
  {
    "sender": "Aamir | عامر",
    "text": "You sent an attachment.",
    "time": "Mar 05, 2025 2:30 am",
    "reactions": [],
    "kind": "msg"
  },
  {
    "sender": "Aamir | عامر",
    "text": "You sent an attachment.",
    "time": "Mar 05, 2025 2:32 am",
    "reactions": [
      {
        "reactor": "Bushra Khan",
        "emoji": "❤️"
      }
    ],
    "kind": "msg"
  },
  {
    "sender": "Bushra Khan",
    "text": "I don’t like carrot",
    "time": "Mar 05, 2025 2:35 am",
    "reactions": [],
    "kind": "msg"
  },
  {
    "sender": "Aamir | عامر",
    "text": "Got it",
    "time": "Mar 05, 2025 2:35 am",
    "reactions": [],
    "kind": "msg"
  },
  {
    "sender": "Bushra Khan",
    "text": "You like it sir ?",
    "time": "Mar 05, 2025 2:36 am",
    "reactions": [],
    "kind": "msg"
  },
  {
    "sender": "Aamir | عامر",
    "text": "Not like it like it, but can eat",
    "time": "Mar 05, 2025 2:37 am",
    "reactions": [
      {
        "reactor": "Bushra Khan",
        "emoji": "❤️"
      }
    ],
    "kind": "msg"
  },
  {
    "sender": "Bushra Khan",
    "text": "Okayyy",
    "time": "Mar 05, 2025 2:39 am",
    "reactions": [
      {
        "reactor": "Aamir | عامر",
        "emoji": "❤️"
      }
    ],
    "kind": "msg"
  },
  {
    "sender": "Aamir | عامر",
    "text": "Sid you see the caption of the reel ma’am",
    "time": "Mar 05, 2025 2:45 am",
    "reactions": [],
    "kind": "msg"
  },
  {
    "sender": "Aamir | عامر",
    "text": "Suhoor one",
    "time": "Mar 05, 2025 2:46 am",
    "reactions": [],
    "kind": "msg"
  },
  {
    "sender": "Bushra Khan",
    "text": "Yepp",
    "time": "Mar 05, 2025 2:47 am",
    "reactions": [],
    "kind": "msg"
  },
  {
    "sender": "Bushra Khan",
    "text": "It’s easy ones",
    "time": "Mar 05, 2025 2:47 am",
    "reactions": [
      {
        "reactor": "Aamir | عامر",
        "emoji": "❤️"
      }
    ],
    "kind": "msg"
  },
  {
    "sender": "Aamir | عامر",
    "text": "Yuppp",
    "time": "Mar 05, 2025 2:48 am",
    "reactions": [],
    "kind": "msg"
  },
  {
    "sender": "Aamir | عامر",
    "text": "I had my interview",
    "time": "Mar 05, 2025 4:10 am",
    "reactions": [
      {
        "reactor": "Bushra Khan",
        "emoji": "❤️"
      }
    ],
    "kind": "msg"
  },
  {
    "sender": "Bushra Khan",
    "text": "How was it sir",
    "time": "Mar 05, 2025 5:12 am",
    "reactions": [],
    "kind": "msg"
  },
  {
    "sender": "Aamir | عامر",
    "text": "It was okay I guess",
    "time": "Mar 05, 2025 5:27 am",
    "reactions": [
      {
        "reactor": "Bushra Khan",
        "emoji": "❤️"
      }
    ],
    "kind": "msg"
  },
  {
    "sender": "Bushra Khan",
    "text": "Okay",
    "time": "Mar 05, 2025 5:35 am",
    "reactions": [
      {
        "reactor": "Aamir | عامر",
        "emoji": "❤️"
      }
    ],
    "kind": "msg"
  },
  {
    "sender": "Bushra Khan",
    "text": "It will be fine",
    "time": "Mar 05, 2025 5:35 am",
    "reactions": [
      {
        "reactor": "Aamir | عامر",
        "emoji": "❤️"
      }
    ],
    "kind": "msg"
  },
  {
    "sender": "Aamir | عامر",
    "text": "Okay ma’am",
    "time": "Mar 05, 2025 5:43 am",
    "reactions": [],
    "kind": "msg"
  },
  {
    "sender": "Aamir | عامر",
    "text": "Came back from namaz",
    "time": "Mar 05, 2025 5:43 am",
    "reactions": [
      {
        "reactor": "Bushra Khan",
        "emoji": "❤️"
      }
    ],
    "kind": "msg"
  },
  {
    "sender": "Bushra Khan",
    "text": "Okay",
    "time": "Mar 05, 2025 6:13 am",
    "reactions": [
      {
        "reactor": "Aamir | عامر",
        "emoji": "❤️"
      }
    ],
    "kind": "msg"
  },
  {
    "sender": "Aamir | عامر",
    "text": "Yes",
    "time": "Mar 05, 2025 6:20 am",
    "reactions": [],
    "kind": "msg"
  },
  {
    "sender": "Aamir | عامر",
    "text": "Did yoy have iftaar",
    "time": "Mar 05, 2025 6:21 am",
    "reactions": [],
    "kind": "msg"
  },
  {
    "sender": "Bushra Khan",
    "text": "Yepp",
    "time": "Mar 05, 2025 6:22 am",
    "reactions": [],
    "kind": "msg"
  },
  {
    "sender": "Bushra Khan",
    "text": "Had watermelon",
    "time": "Mar 05, 2025 6:23 am",
    "reactions": [
      {
        "reactor": "Aamir | عامر",
        "emoji": "❤️"
      }
    ],
    "kind": "msg"
  },
  {
    "sender": "Bushra Khan",
    "text": "And bhjiya",
    "time": "Mar 05, 2025 6:23 am",
    "reactions": [
      {
        "reactor": "Aamir | عامر",
        "emoji": "❤️"
      }
    ],
    "kind": "msg"
  },
  {
    "sender": "Bushra Khan",
    "text": "What did you have",
    "time": "Mar 05, 2025 6:23 am",
    "reactions": [],
    "kind": "msg"
  },
  {
    "sender": "Aamir | عامر",
    "text": "Noice",
    "time": "Mar 05, 2025 6:23 am",
    "reactions": [
      {
        "reactor": "Bushra Khan",
        "emoji": "❤️"
      }
    ],
    "kind": "msg"
  },
  {
    "sender": "Aamir | عامر",
    "text": "I had fruits and bhajiya and samosa",
    "time": "Mar 05, 2025 6:23 am",
    "reactions": [
      {
        "reactor": "Bushra Khan",
        "emoji": "❤️"
      }
    ],
    "kind": "msg"
  },
  {
    "sender": "Bushra Khan",
    "text": "Noiceee",
    "time": "Mar 05, 2025 6:27 am",
    "reactions": [
      {
        "reactor": "Aamir | عامر",
        "emoji": "❤️️"
      }
    ],
    "kind": "msg"
  },
  {
    "sender": "Bushra Khan",
    "text": "They made milk wala roohafza",
    "time": "Mar 05, 2025 6:27 am",
    "reactions": [
      {
        "reactor": "Aamir | عامر",
        "emoji": "❤️️"
      }
    ],
    "kind": "msg"
  },
  {
    "sender": "Aamir | عامر",
    "text": "Noicee 😁",
    "time": "Mar 05, 2025 6:27 am",
    "reactions": [
      {
        "reactor": "Bushra Khan",
        "emoji": "❤️"
      }
    ],
    "kind": "msg"
  },
  {
    "sender": "Bushra Khan",
    "text": "🤩",
    "time": "Mar 05, 2025 6:27 am",
    "reactions": [
      {
        "reactor": "Aamir | عامر",
        "emoji": "❤️️"
      }
    ],
    "kind": "msg"
  },
  {
    "sender": "Aamir | عامر",
    "text": "call par ho",
    "time": "Mar 05, 2025 8:03 am",
    "reactions": [],
    "kind": "msg"
  },
  {
    "sender": "Bushra Khan",
    "text": "Nhi",
    "time": "Mar 05, 2025 8:04 am",
    "reactions": [],
    "kind": "msg"
  },
  {
    "sender": "Bushra Khan",
    "text": "I’ll take the break at 9.35",
    "time": "Mar 05, 2025 8:04 am",
    "reactions": [],
    "kind": "msg"
  },
  {
    "sender": "Aamir | عامر",
    "text": "okay ma'am",
    "time": "Mar 05, 2025 8:04 am",
    "reactions": [],
    "kind": "msg"
  },
  {
    "sender": "Bushra Khan",
    "text": "Took break",
    "time": "Mar 05, 2025 8:11 am",
    "reactions": [
      {
        "reactor": "Aamir | عامر",
        "emoji": "❤️️"
      }
    ],
    "kind": "msg"
  },
  {
    "sender": "Aamir | عامر",
    "text": "okay ma'am",
    "time": "Mar 05, 2025 8:13 am",
    "reactions": [],
    "kind": "msg"
  },
  {
    "sender": "Aamir | عامر",
    "text": "You sent an attachment.",
    "time": "Mar 05, 2025 9:06 am",
    "reactions": [
      {
        "reactor": "Bushra Khan",
        "emoji": "😂"
      }
    ],
    "kind": "msg"
  },
  {
    "sender": "Aamir | عامر",
    "text": "You sent an attachment.",
    "time": "Mar 05, 2025 9:12 am",
    "reactions": [
      {
        "reactor": "Bushra Khan",
        "emoji": "❤️"
      }
    ],
    "kind": "msg"
  },
  {
    "sender": "Bushra Khan",
    "text": "You like them",
    "time": "Mar 05, 2025 9:12 am",
    "reactions": [],
    "kind": "msg"
  },
  {
    "sender": "Aamir | عامر",
    "text": "Yupp sheeps are cute",
    "time": "Mar 05, 2025 9:13 am",
    "reactions": [
      {
        "reactor": "Bushra Khan",
        "emoji": "❤️"
      }
    ],
    "kind": "msg"
  },
  {
    "sender": "Bushra Khan",
    "text": "I know",
    "time": "Mar 05, 2025 9:13 am",
    "reactions": [],
    "kind": "msg"
  },
  {
    "sender": "Bushra Khan",
    "text": "They are drunk",
    "time": "Mar 05, 2025 9:13 am",
    "reactions": [],
    "kind": "msg"
  }
]