[
  {
    "sender": "Aamir | عامر",
    "text": "Will come okayBistar kar k",
    "time": "Mar 19, 2025 11:06 am",
    "reactions": [],
    "kind": "msg"
  },
  {
    "sender": "Bushra Khan",
    "text": "Jii",
    "time": "Mar 19, 2025 11:06 am",
    "reactions": [
      {
        "reactor": "Aamir | عامر",
        "emoji": "❤️"
      }
    ],
    "kind": "msg"
  },
  {
    "sender": "Aamir | عامر",
    "text": "Am done",
    "time": "Mar 19, 2025 11:12 am",
    "reactions": [
      {
        "reactor": "Bushra Khan",
        "emoji": "❤️"
      }
    ],
    "kind": "msg"
  },
  {
    "sender": "Aamir | عامر",
    "text": "I feel too fulll",
    "time": "Mar 19, 2025 11:13 am",
    "reactions": [
      {
        "reactor": "Bushra Khan",
        "emoji": "❤️"
      }
    ],
    "kind": "msg"
  },
  {
    "sender": "Bushra Khan",
    "text": "Hehe",
    "time": "Mar 19, 2025 11:13 am",
    "reactions": [
      {
        "reactor": "Aamir | عامر",
        "emoji": "❤️"
      }
    ],
    "kind": "msg"
  },
  {
    "sender": "Bushra Khan",
    "text": "😁",
    "time": "Mar 19, 2025 11:13 am",
    "reactions": [
      {
        "reactor": "Aamir | عامر",
        "emoji": "❤️"
      }
    ],
    "kind": "msg"
  },
  {
    "sender": "Aamir | عامر",
    "text": "😁",
    "time": "Mar 19, 2025 11:13 am",
    "reactions": [
      {
        "reactor": "Bushra Khan",
        "emoji": "❤️"
      }
    ],
    "kind": "msg"
  },
  {
    "sender": "Aamir | عامر",
    "text": "Dekhna hai",
    "time": "Mar 19, 2025 11:15 am",
    "reactions": [],
    "kind": "msg"
  },
  {
    "sender": "Bushra Khan",
    "text": "Kay",
    "time": "Mar 19, 2025 11:15 am",
    "reactions": [],
    "kind": "msg"
  },
  {
    "sender": "Aamir | عامر",
    "text": "Series",
    "time": "Mar 19, 2025 11:16 am",
    "reactions": [],
    "kind": "msg"
  },
  {
    "sender": "Bushra Khan",
    "text": "Yep",
    "time": "Mar 19, 2025 11:17 am",
    "reactions": [
      {
        "reactor": "Aamir | عامر",
        "emoji": "❤️"
      }
    ],
    "kind": "msg"
  },
  {
    "sender": "Aamir | عامر",
    "text": "Theek hai",
    "time": "Mar 19, 2025 11:17 am",
    "reactions": [
      {
        "reactor": "Bushra Khan",
        "emoji": "❤️"
      }
    ],
    "kind": "msg"
  },
  {
    "sender": "Aamir | عامر",
    "text": "Did you leave",
    "time": "Mar 19, 2025 12:05 pm",
    "reactions": [],
    "kind": "msg"
  },
  {
    "sender": "Bushra Khan",
    "text": "Nope",
    "time": "Mar 19, 2025 12:05 pm",
    "reactions": [],
    "kind": "msg"
  },
  {
    "sender": "Bushra Khan",
    "text": "Watching",
    "time": "Mar 19, 2025 12:05 pm",
    "reactions": [],
    "kind": "msg"
  },
  {
    "sender": "Aamir | عامر",
    "text": "Okay",
    "time": "Mar 19, 2025 12:05 pm",
    "reactions": [],
    "kind": "msg"
  },
  {
    "sender": "Bushra Khan",
    "text": "😁",
    "time": "Mar 19, 2025 12:19 pm",
    "reactions": [],
    "kind": "msg"
  },
  {
    "sender": "Aamir | عامر",
    "text": "Sleep well okau",
    "time": "Mar 19, 2025 1:26 pm",
    "reactions": [
      {
        "reactor": "Bushra Khan",
        "emoji": "❤️"
      }
    ],
    "kind": "msg"
  },
  {
    "sender": "Aamir | عامر",
    "text": "Sleep well okay (edited)",
    "time": "Mar 19, 2025 1:26 pm",
    "reactions": [
      {
        "reactor": "Bushra Khan",
        "emoji": "❤️"
      }
    ],
    "kind": "msg"
  },
  {
    "sender": "Bushra Khan",
    "text": "You too",
    "time": "Mar 19, 2025 1:26 pm",
    "reactions": [
      {
        "reactor": "Aamir | عامر",
        "emoji": "❤️"
      }
    ],
    "kind": "msg"
  },
  {
    "sender": "Aamir | عامر",
    "text": "👋❤️❤️❤️",
    "time": "Mar 19, 2025 1:26 pm",
    "reactions": [],
    "kind": "msg"
  },
  {
    "sender": "Bushra Khan",
    "text": "Allah hafiz",
    "time": "Mar 19, 2025 1:26 pm",
    "reactions": [],
    "kind": "msg"
  },
  {
    "sender": "Bushra Khan",
    "text": "👋♥️♥️♥️",
    "time": "Mar 19, 2025 1:26 pm",
    "reactions": [
      {
        "reactor": "Aamir | عامر",
        "emoji": "❤️"
      }
    ],
    "kind": "msg"
  },
  {
    "sender": "Aamir | عامر",
    "text": "Allah hafiz",
    "time": "Mar 19, 2025 1:26 pm",
    "reactions": [],
    "kind": "msg"
  },
  {
    "sender": "Bushra Khan",
    "text": "Have woken up",
    "time": "Mar 19, 2025 3:32 pm",
    "reactions": [],
    "kind": "msg"
  },
  {
    "sender": "Bushra Khan",
    "text": "Was doing namaz",
    "time": "Mar 19, 2025 3:32 pm",
    "reactions": [
      {
        "reactor": "Aamir | عامر",
        "emoji": "❤️"
      }
    ],
    "kind": "msg"
  },
  {
    "sender": "Bushra Khan",
    "text": "Couldn’t pick up",
    "time": "Mar 19, 2025 3:32 pm",
    "reactions": [],
    "kind": "msg"
  },
  {
    "sender": "Aamir | عامر",
    "text": "It’s okay ma’am",
    "time": "Mar 19, 2025 3:32 pm",
    "reactions": [
      {
        "reactor": "Bushra Khan",
        "emoji": "❤️"
      }
    ],
    "kind": "msg"
  },
  {
    "sender": "Aamir | عامر",
    "text": "Have sehri okay",
    "time": "Mar 19, 2025 3:33 pm",
    "reactions": [],
    "kind": "msg"
  },
  {
    "sender": "Bushra Khan",
    "text": "Yes",
    "time": "Mar 19, 2025 3:33 pm",
    "reactions": [],
    "kind": "msg"
  },
  {
    "sender": "Bushra Khan",
    "text": "You too",
    "time": "Mar 19, 2025 3:33 pm",
    "reactions": [],
    "kind": "msg"
  },
  {
    "sender": "Aamir | عامر",
    "text": "Yes maa",
    "time": "Mar 19, 2025 3:33 pm",
    "reactions": [],
    "kind": "msg"
  },
  {
    "sender": "Aamir | عامر",
    "text": "Yes ma’am (edited)",
    "time": "Mar 19, 2025 3:33 pm",
    "reactions": [],
    "kind": "msg"
  },
  {
    "sender": "Aamir | عامر",
    "text": "Will sleep ma’am",
    "time": "Mar 19, 2025 3:43 pm",
    "reactions": [
      {
        "reactor": "Bushra Khan",
        "emoji": "❤️"
      }
    ],
    "kind": "msg"
  },
  {
    "sender": "Aamir | عامر",
    "text": "You too have and sleep soon okay",
    "time": "Mar 19, 2025 3:43 pm",
    "reactions": [],
    "kind": "msg"
  },
  {
    "sender": "Bushra Khan",
    "text": "Yepp",
    "time": "Mar 19, 2025 3:47 pm",
    "reactions": [],
    "kind": "msg"
  },
  {
    "sender": "Aamir | عامر",
    "text": "Dod you start working",
    "time": "Mar 20, 2025 12:25 am",
    "reactions": [],
    "kind": "msg"
  },
  {
    "sender": "Bushra Khan",
    "text": "Yepp",
    "time": "Mar 20, 2025 12:30 am",
    "reactions": [
      {
        "reactor": "Aamir | عامر",
        "emoji": "❤️"
      }
    ],
    "kind": "msg"
  },
  {
    "sender": "Bushra Khan",
    "text": "I couldn’t pray",
    "time": "Mar 20, 2025 12:30 am",
    "reactions": [],
    "kind": "msg"
  },
  {
    "sender": "Aamir | عامر",
    "text": "Ohh okayThe timing is such",
    "time": "Mar 20, 2025 12:31 am",
    "reactions": [],
    "kind": "msg"
  },
  {
    "sender": "Bushra Khan",
    "text": "Yepp",
    "time": "Mar 20, 2025 12:59 am",
    "reactions": [],
    "kind": "msg"
  },
  {
    "sender": "Bushra Khan",
    "text": "Prayed noe",
    "time": "Mar 20, 2025 12:59 am",
    "reactions": [
      {
        "reactor": "Aamir | عامر",
        "emoji": "❤️"
      }
    ],
    "kind": "msg"
  },
  {
    "sender": "Aamir | عامر",
    "text": "Okay ma’am",
    "time": "Mar 20, 2025 1:02 am",
    "reactions": [],
    "kind": "msg"
  },
  {
    "sender": "Aamir | عامر",
    "text": "I did too",
    "time": "Mar 20, 2025 1:02 am",
    "reactions": [
      {
        "reactor": "Bushra Khan",
        "emoji": "❤️"
      }
    ],
    "kind": "msg"
  },
  {
    "sender": "Bushra Khan",
    "text": "Good",
    "time": "Mar 20, 2025 1:02 am",
    "reactions": [
      {
        "reactor": "Aamir | عامر",
        "emoji": "❤️"
      }
    ],
    "kind": "msg"
  },
  {
    "sender": "Bushra Khan",
    "text": "You know",
    "time": "Mar 20, 2025 1:39 am",
    "reactions": [],
    "kind": "msg"
  },
  {
    "sender": "Aamir | عامر",
    "text": "What ma’am",
    "time": "Mar 20, 2025 1:41 am",
    "reactions": [],
    "kind": "msg"
  },
  {
    "sender": "Bushra Khan",
    "text": "The lady we had asked to work when the house help was not there",
    "time": "Mar 20, 2025 1:41 am",
    "reactions": [],
    "kind": "msg"
  },
  {
    "sender": "Bushra Khan",
    "text": "Was asking for her money",
    "time": "Mar 20, 2025 1:41 am",
    "reactions": [],
    "kind": "msg"
  },
  {
    "sender": "Bushra Khan",
    "text": "And i gave 500 ka note",
    "time": "Mar 20, 2025 1:41 am",
    "reactions": [],
    "kind": "msg"
  },
  {
    "sender": "Bushra Khan",
    "text": "Cause I didn’t have change",
    "time": "Mar 20, 2025 1:42 am",
    "reactions": [],
    "kind": "msg"
  },
  {
    "sender": "Bushra Khan",
    "text": "And that women is saying won’t g",
    "time": "Mar 20, 2025 1:42 am",
    "reactions": [],
    "kind": "msg"
  },
  {
    "sender": "Bushra Khan",
    "text": "Give back now",
    "time": "Mar 20, 2025 1:42 am",
    "reactions": [],
    "kind": "msg"
  },
  {
    "sender": "Bushra Khan",
    "text": "I am getting blood boiled",
    "time": "Mar 20, 2025 1:42 am",
    "reactions": [],
    "kind": "msg"
  },
  {
    "sender": "Aamir | عامر",
    "text": "Whattt did she say at the same time you gave",
    "time": "Mar 20, 2025 1:42 am",
    "reactions": [],
    "kind": "msg"
  },
  {
    "sender": "Bushra Khan",
    "text": "She said will bring back",
    "time": "Mar 20, 2025 1:43 am",
    "reactions": [],
    "kind": "msg"
  },
  {
    "sender": "Bushra Khan",
    "text": "I would not have given",
    "time": "Mar 20, 2025 1:43 am",
    "reactions": [],
    "kind": "msg"
  },
  {
    "sender": "Bushra Khan",
    "text": "But she kept knocking while I was on call",
    "time": "Mar 20, 2025 1:43 am",
    "reactions": [],
    "kind": "msg"
  },
  {
    "sender": "Aamir | عامر",
    "text": "How much you had to give",
    "time": "Mar 20, 2025 1:43 am",
    "reactions": [],
    "kind": "msg"
  },
  {
    "sender": "Bushra Khan",
    "text": "100",
    "time": "Mar 20, 2025 1:43 am",
    "reactions": [],
    "kind": "msg"
  },
  {
    "sender": "Aamir | عامر",
    "text": "Whatttt, did she plainly say she won’t give or is she making reasons",
    "time": "Mar 20, 2025 1:44 am",
    "reactions": [],
    "kind": "msg"
  },
  {
    "sender": "Bushra Khan",
    "text": "Just saying won’t give",
    "time": "Mar 20, 2025 1:45 am",
    "reactions": [],
    "kind": "msg"
  },
  {
    "sender": "Bushra Khan",
    "text": "And went away",
    "time": "Mar 20, 2025 1:45 am",
    "reactions": [],
    "kind": "msg"
  },
  {
    "sender": "Bushra Khan",
    "text": "Mum knew here",
    "time": "Mar 20, 2025 1:45 am",
    "reactions": [],
    "kind": "msg"
  },
  {
    "sender": "Bushra Khan",
    "text": "That’s why we called",
    "time": "Mar 20, 2025 1:45 am",
    "reactions": [],
    "kind": "msg"
  },
  {
    "sender": "Aamir | عامر",
    "text": "Go with your sister at her home aur bolo uskoIsn’t it stealing in the daylight",
    "time": "Mar 20, 2025 1:46 am",
    "reactions": [],
    "kind": "msg"
  },
  {
    "sender": "Bushra Khan",
    "text": "I’ll wait for her to come",
    "time": "Mar 20, 2025 1:46 am",
    "reactions": [],
    "kind": "msg"
  },
  {
    "sender": "Bushra Khan",
    "text": "My sis",
    "time": "Mar 20, 2025 1:46 am",
    "reactions": [],
    "kind": "msg"
  },
  {
    "sender": "Bushra Khan",
    "text": "Was on call",
    "time": "Mar 20, 2025 1:46 am",
    "reactions": [],
    "kind": "msg"
  },
  {
    "sender": "Aamir | عامر",
    "text": "Okay ma’am",
    "time": "Mar 20, 2025 1:46 am",
    "reactions": [],
    "kind": "msg"
  },
  {
    "sender": "Aamir | عامر",
    "text": "That’s like too muchAise logo ko to kya hi bolne i am getting angry now",
    "time": "Mar 20, 2025 1:47 am",
    "reactions": [],
    "kind": "msg"
  },
  {
    "sender": "Aamir | عامر",
    "text": "These people deserve to be low life",
    "time": "Mar 20, 2025 1:47 am",
    "reactions": [],
    "kind": "msg"
  },
  {
    "sender": "Bushra Khan",
    "text": "Literally fuming",
    "time": "Mar 20, 2025 1:47 am",
    "reactions": [],
    "kind": "msg"
  },
  {
    "sender": "Aamir | عامر",
    "text": "Me tooHow can someone say no plainlyWhat is this",
    "time": "Mar 20, 2025 1:48 am",
    "reactions": [],
    "kind": "msg"
  },
  {
    "sender": "Aamir | عامر",
    "text": "Don’t worry for now okayWait for some timeLet your sister come and then go to her place",
    "time": "Mar 20, 2025 1:48 am",
    "reactions": [],
    "kind": "msg"
  },
  {
    "sender": "Bushra Khan",
    "text": "Yeppp",
    "time": "Mar 20, 2025 1:48 am",
    "reactions": [],
    "kind": "msg"
  },
  {
    "sender": "Aamir | عامر",
    "text": "She lives nearby right",
    "time": "Mar 20, 2025 1:48 am",
    "reactions": [],
    "kind": "msg"
  },
  {
    "sender": "Bushra Khan",
    "text": "Yep she does",
    "time": "Mar 20, 2025 1:49 am",
    "reactions": [],
    "kind": "msg"
  },
  {
    "sender": "Aamir | عامر",
    "text": "Is she muslim",
    "time": "Mar 20, 2025 1:49 am",
    "reactions": [],
    "kind": "msg"
  },
  {
    "sender": "Aamir | عامر",
    "text": "Or better go with your younger maamu ma’am",
    "time": "Mar 20, 2025 1:50 am",
    "reactions": [],
    "kind": "msg"
  },
  {
    "sender": "Aamir | عامر",
    "text": "Like you both can take him as well",
    "time": "Mar 20, 2025 1:50 am",
    "reactions": [],
    "kind": "msg"
  },
  {
    "sender": "Bushra Khan",
    "text": "Nope she is non Muslim",
    "time": "Mar 20, 2025 1:50 am",
    "reactions": [],
    "kind": "msg"
  },
  {
    "sender": "Bushra Khan",
    "text": "Don’t know if he would come",
    "time": "Mar 20, 2025 1:51 am",
    "reactions": [],
    "kind": "msg"
  },
  {
    "sender": "Aamir | عامر",
    "text": "StupidGaali dene ka man ho raha hai",
    "time": "Mar 20, 2025 1:51 am",
    "reactions": [],
    "kind": "msg"
  },
  {
    "sender": "Aamir | عامر",
    "text": "Just ask once okayYou never know how these people react",
    "time": "Mar 20, 2025 1:52 am",
    "reactions": [],
    "kind": "msg"
  },
  {
    "sender": "Aamir | عامر",
    "text": "If you going in night ask your maamu or you can go in morning",
    "time": "Mar 20, 2025 1:52 am",
    "reactions": [],
    "kind": "msg"
  },
  {
    "sender": "Aamir | عامر",
    "text": "Don’t worry for now okay ma’amYou have work tooThese stupid people deserve all bad things happening to them",
    "time": "Mar 20, 2025 1:53 am",
    "reactions": [],
    "kind": "msg"
  },
  {
    "sender": "Aamir | عامر",
    "text": "He didn’t call cause you were on call rigjt",
    "time": "Mar 20, 2025 2:06 am",
    "reactions": [],
    "kind": "msg"
  },
  {
    "sender": "Aamir | عامر",
    "text": "He didn’t call cause you were on call right (edited)",
    "time": "Mar 20, 2025 2:06 am",
    "reactions": [],
    "kind": "msg"
  },
  {
    "sender": "Bushra Khan",
    "text": "Was on hold for too long",
    "time": "Mar 20, 2025 2:10 am",
    "reactions": [],
    "kind": "msg"
  },
  {
    "sender": "Bushra Khan",
    "text": "Wanted to just tell you",
    "time": "Mar 20, 2025 2:10 am",
    "reactions": [],
    "kind": "msg"
  },
  {
    "sender": "Aamir | عامر",
    "text": "Okay ma’amThank you for tellingYou don’t worry okayGiven that she is bewadi aurat there you shouldn’t fight with her on your own okay please",
    "time": "Mar 20, 2025 2:11 am",
    "reactions": [
      {
        "reactor": "Bushra Khan",
        "emoji": "❤️"
      }
    ],
    "kind": "msg"
  },
  {
    "sender": "Aamir | عامر",
    "text": "Okay ma’amThank you for tellingYou don’t worry okayGiven that she is bewadi auratyou shouldn’t fight with her on your own okay please (edited)",
    "time": "Mar 20, 2025 2:12 am",
    "reactions": [
      {
        "reactor": "Bushra Khan",
        "emoji": "❤️"
      }
    ],
    "kind": "msg"
  },
  {
    "sender": "Bushra Khan",
    "text": "Yepp",
    "time": "Mar 20, 2025 2:28 am",
    "reactions": [
      {
        "reactor": "Aamir | عامر",
        "emoji": "❤️"
      }
    ],
    "kind": "msg"
  },
  {
    "sender": "Bushra Khan",
    "text": "Won’t do",
    "time": "Mar 20, 2025 2:28 am",
    "reactions": [
      {
        "reactor": "Aamir | عامر",
        "emoji": "❤️"
      }
    ],
    "kind": "msg"
  },
  {
    "sender": "Bushra Khan",
    "text": "Pakka",
    "time": "Mar 20, 2025 2:28 am",
    "reactions": [
      {
        "reactor": "Aamir | عامر",
        "emoji": "❤️"
      }
    ],
    "kind": "msg"
  },
  {
    "sender": "Aamir | عامر",
    "text": "Yes, Thank you!",
    "time": "Mar 20, 2025 2:29 am",
    "reactions": [
      {
        "reactor": "Bushra Khan",
        "emoji": "❤️"
      }
    ],
    "kind": "msg"
  },
  {
    "sender": "Bushra Khan",
    "text": "Don’t wanna work",
    "time": "Mar 20, 2025 2:29 am",
    "reactions": [],
    "kind": "msg"
  },
  {
    "sender": "Aamir | عامر",
    "text": "I know ma’am",
    "time": "Mar 20, 2025 2:29 am",
    "reactions": [],
    "kind": "msg"
  },
  {
    "sender": "Aamir | عامر",
    "text": "Sometimes we just have toDon’t worry, I will be here",
    "time": "Mar 20, 2025 2:30 am",
    "reactions": [
      {
        "reactor": "Bushra Khan",
        "emoji": "❤️"
      }
    ],
    "kind": "msg"
  },
  {
    "sender": "Bushra Khan",
    "text": "Yep",
    "time": "Mar 20, 2025 2:31 am",
    "reactions": [
      {
        "reactor": "Aamir | عامر",
        "emoji": "❤️"
      }
    ],
    "kind": "msg"
  },
  {
    "sender": "Aamir | عامر",
    "text": "Yess",
    "time": "Mar 20, 2025 2:31 am",
    "reactions": [
      {
        "reactor": "Bushra Khan",
        "emoji": "❤️"
      }
    ],
    "kind": "msg"
  },
  {
    "sender": "Aamir | عامر",
    "text": "You sent an attachment.",
    "time": "Mar 20, 2025 2:38 am",
    "reactions": [
      {
        "reactor": "Bushra Khan",
        "emoji": "❤️"
      }
    ],
    "kind": "msg"
  },
  {
    "sender": "Aamir | عامر",
    "text": "This was made that day",
    "time": "Mar 20, 2025 2:38 am",
    "reactions": [],
    "kind": "msg"
  },
  {
    "sender": "Bushra Khan",
    "text": "Noice",
    "time": "Mar 20, 2025 3:03 am",
    "reactions": [
      {
        "reactor": "Aamir | عامر",
        "emoji": "❤️"
      }
    ],
    "kind": "msg"
  },
  {
    "sender": "Aamir | عامر",
    "text": "Cylinder khatam ho gaya tha",
    "time": "Mar 20, 2025 3:16 am",
    "reactions": [],
    "kind": "msg"
  },
  {
    "sender": "Aamir | عامر",
    "text": "To had to do idhar se udhar 🥲",
    "time": "Mar 20, 2025 3:16 am",
    "reactions": [],
    "kind": "msg"
  },
  {
    "sender": "Bushra Khan",
    "text": "🥲",
    "time": "Mar 20, 2025 3:48 am",
    "reactions": [],
    "kind": "msg"
  },
  {
    "sender": "Bushra Khan",
    "text": "It’s another hassle",
    "time": "Mar 20, 2025 3:48 am",
    "reactions": [
      {
        "reactor": "Aamir | عامر",
        "emoji": "❤️"
      }
    ],
    "kind": "msg"
  },
  {
    "sender": "Aamir | عامر",
    "text": "Yuppp",
    "time": "Mar 20, 2025 4:05 am",
    "reactions": [],
    "kind": "msg"
  },
  {
    "sender": "Aamir | عامر",
    "text": "Did you take break ma’am",
    "time": "Mar 20, 2025 5:15 am",
    "reactions": [],
    "kind": "msg"
  },
  {
    "sender": "Bushra Khan",
    "text": "Not yet",
    "time": "Mar 20, 2025 5:21 am",
    "reactions": [],
    "kind": "msg"
  },
  {
    "sender": "Bushra Khan",
    "text": "Sir",
    "time": "Mar 20, 2025 5:21 am",
    "reactions": [],
    "kind": "msg"
  },
  {
    "sender": "Bushra Khan",
    "text": "Is it okay if you can tell when the azan starts",
    "time": "Mar 20, 2025 5:21 am",
    "reactions": [],
    "kind": "msg"
  },
  {
    "sender": "Aamir | عامر",
    "text": "Am sorry",
    "time": "Mar 20, 2025 5:38 am",
    "reactions": [],
    "kind": "msg"
  },
  {
    "sender": "Aamir | عامر",
    "text": "Didn’t see",
    "time": "Mar 20, 2025 5:38 am",
    "reactions": [],
    "kind": "msg"
  },
  {
    "sender": "Aamir | عامر",
    "text": "It was at 6:52",
    "time": "Mar 20, 2025 5:39 am",
    "reactions": [],
    "kind": "msg"
  },
  {
    "sender": "Bushra Khan",
    "text": "It’s okay",
    "time": "Mar 20, 2025 5:42 am",
    "reactions": [],
    "kind": "msg"
  },
  {
    "sender": "Aamir | عامر",
    "text": "Did you have iftaar ma’am",
    "time": "Mar 20, 2025 5:45 am",
    "reactions": [],
    "kind": "msg"
  },
  {
    "sender": "Bushra Khan",
    "text": "Yepp",
    "time": "Mar 20, 2025 5:45 am",
    "reactions": [
      {
        "reactor": "Aamir | عامر",
        "emoji": "❤️"
      }
    ],
    "kind": "msg"
  },
  {
    "sender": "Bushra Khan",
    "text": "The dates are nice",
    "time": "Mar 20, 2025 5:45 am",
    "reactions": [
      {
        "reactor": "Aamir | عامر",
        "emoji": "❤️"
      }
    ],
    "kind": "msg"
  },
  {
    "sender": "Aamir | عامر",
    "text": "Okay ma’am",
    "time": "Mar 20, 2025 5:45 am",
    "reactions": [],
    "kind": "msg"
  },
  {
    "sender": "Aamir | عامر",
    "text": "What else you had",
    "time": "Mar 20, 2025 5:45 am",
    "reactions": [],
    "kind": "msg"
  },
  {
    "sender": "Aamir | عامر",
    "text": "Did they not bring iftaar ma’am",
    "time": "Mar 20, 2025 5:47 am",
    "reactions": [],
    "kind": "msg"
  },
  {
    "sender": "Bushra Khan",
    "text": "They don’t have gas so didn’t make anything",
    "time": "Mar 20, 2025 5:48 am",
    "reactions": [],
    "kind": "msg"
  },
  {
    "sender": "Aamir | عامر",
    "text": "Okaay",
    "time": "Mar 20, 2025 5:48 am",
    "reactions": [],
    "kind": "msg"
  },
  {
    "sender": "Aamir | عامر",
    "text": "Are you on call or you got time ma’am",
    "time": "Mar 20, 2025 5:48 am",
    "reactions": [],
    "kind": "msg"
  },
  {
    "sender": "Bushra Khan",
    "text": "Am on call",
    "time": "Mar 20, 2025 5:48 am",
    "reactions": [],
    "kind": "msg"
  },
  {
    "sender": "Aamir | عامر",
    "text": "Okay",
    "time": "Mar 20, 2025 5:49 am",
    "reactions": [],
    "kind": "msg"
  },
  {
    "sender": "Aamir | عامر",
    "text": "Have something soon okay",
    "time": "Mar 20, 2025 5:49 am",
    "reactions": [],
    "kind": "msg"
  },
  {
    "sender": "Bushra Khan",
    "text": "Yepp",
    "time": "Mar 20, 2025 5:49 am",
    "reactions": [
      {
        "reactor": "Aamir | عامر",
        "emoji": "❤️"
      }
    ],
    "kind": "msg"
  },
  {
    "sender": "Aamir | عامر",
    "text": "I did namaz",
    "time": "Mar 20, 2025 5:49 am",
    "reactions": [
      {
        "reactor": "Bushra Khan",
        "emoji": "❤️"
      }
    ],
    "kind": "msg"
  },
  {
    "sender": "Bushra Khan",
    "text": "Good",
    "time": "Mar 20, 2025 6:02 am",
    "reactions": [
      {
        "reactor": "Aamir | عامر",
        "emoji": "❤️"
      }
    ],
    "kind": "msg"
  },
  {
    "sender": "Aamir | عامر",
    "text": "Am going to gym ma’am",
    "time": "Mar 20, 2025 8:33 am",
    "reactions": [],
    "kind": "msg"
  },
  {
    "sender": "Aamir | عامر",
    "text": "Did you take break",
    "time": "Mar 20, 2025 8:34 am",
    "reactions": [],
    "kind": "msg"
  },
  {
    "sender": "Bushra Khan",
    "text": "Almost logged out",
    "time": "Mar 20, 2025 9:14 am",
    "reactions": [],
    "kind": "msg"
  },
  {
    "sender": "Bushra Khan",
    "text": "Logged out",
    "time": "Mar 20, 2025 9:23 am",
    "reactions": [
      {
        "reactor": "Aamir | عامر",
        "emoji": "❤️"
      }
    ],
    "kind": "msg"
  },
  {
    "sender": "Aamir | عامر",
    "text": "Will leave too soon",
    "time": "Mar 20, 2025 9:28 am",
    "reactions": [
      {
        "reactor": "Bushra Khan",
        "emoji": "❤️"
      }
    ],
    "kind": "msg"
  },
  {
    "sender": "Bushra Khan",
    "text": "Okay",
    "time": "Mar 20, 2025 9:41 am",
    "reactions": [
      {
        "reactor": "Aamir | عامر",
        "emoji": "❤️"
      }
    ],
    "kind": "msg"
  },
  {
    "sender": "Aamir | عامر",
    "text": "You sent an attachment.",
    "time": "Mar 20, 2025 10:51 am",
    "reactions": [],
    "kind": "msg"
  },
  {
    "sender": "Aamir | عامر",
    "text": "Did you sleep ma’am",
    "time": "Mar 20, 2025 11:52 am",
    "reactions": [],
    "kind": "msg"
  },
  {
    "sender": "Bushra Khan",
    "text": "Noppeeee",
    "time": "Mar 20, 2025 11:55 am",
    "reactions": [],
    "kind": "msg"
  },
  {
    "sender": "Aamir | عامر",
    "text": "What are you doing",
    "time": "Mar 20, 2025 11:56 am",
    "reactions": [],
    "kind": "msg"
  },
  {
    "sender": "Bushra Khan",
    "text": "Nothing",
    "time": "Mar 20, 2025 11:56 am",
    "reactions": [],
    "kind": "msg"
  },
  {
    "sender": "Bushra Khan",
    "text": "Have to do bistar",
    "time": "Mar 20, 2025 11:57 am",
    "reactions": [],
    "kind": "msg"
  },
  {
    "sender": "Bushra Khan",
    "text": "Are you sleepy sir",
    "time": "Mar 20, 2025 11:57 am",
    "reactions": [],
    "kind": "msg"
  },
  {
    "sender": "Aamir | عامر",
    "text": "Nope",
    "time": "Mar 20, 2025 11:57 am",
    "reactions": [],
    "kind": "msg"
  },
  {
    "sender": "Aamir | عامر",
    "text": "Are you",
    "time": "Mar 20, 2025 11:57 am",
    "reactions": [],
    "kind": "msg"
  },
  {
    "sender": "Bushra Khan",
    "text": "Nope",
    "time": "Mar 20, 2025 11:57 am",
    "reactions": [
      {
        "reactor": "Aamir | عامر",
        "emoji": "❤️"
      }
    ],
    "kind": "msg"
  },
  {
    "sender": "Aamir | عامر",
    "text": "Pkay",
    "time": "Mar 20, 2025 11:58 am",
    "reactions": [],
    "kind": "msg"
  }
]